Metadata-Version: 2.1
Name: pyfnutils
Version: 1.4
Summary: Small utility functions for Python: logging, parallel tasks, zstd
Author: Charles E. Vejnar
License: Mozilla Public License 2.0 (MPL 2.0)
Project-URL: homepage, https://git.sr.ht/~vejnar/pyfnutils
Requires-Python: >=3.8
License-File: LICENSE
